{"parameters": {"filtering_params": {"discard_samples": true, "apply_filter": true, "filter_mode": "time_window", "k": 5, "nm": 5, "ns": 2, "s": 3, "lb_in": 5, "lb_out": 5, "handle_5": false, "handle_6": false}, "signal_params": {"prediction_mode": "max", "m_before": 10, "m_after": 5, "part_mode": "median"}}, "SE": [9, 9, 36, 36, 25, 1, 4, 1, 16, 36, 9, 4, 25, 4, 16, 16, 9, 0, 1, 36, 9, 9, 1, 0, 1, 1, 1, 0, 64], "AE": [3, 3, 6, 6, 5, 1, 2, 1, 4, 6, 3, 2, 5, 2, 4, 4, 3, 0, 1, 6, 3, 3, 1, 0, 1, 1, 1, 0, 8], "CTD": [4, 3, 6, 3, 5, 1, 5, 0, 2, 5, 2, 6, 7, 48, 4, 6, 0, 0, 1, 3, 2, 2, 1, 0, 1, 1, 7, 3, 8]}